untp_models/__init__.py
untp_models/base.py
untp_models/codes.py
untp_models/conformity_credential.py
untp_models-0.1.1.dist-info/METADATA
untp_models-0.1.1.dist-info/WHEEL
untp_models-0.1.1.dist-info/licenses/LICENSE
untp_models-0.1.1.dist-info/RECORD
