Metadata-Version: 2.3
Name: untp_models
Version: 0.1.1
Summary: A python implementation of the UNTP data models
Project-URL: Homepage, https://github.com/Jsyro/untp-models
Author-email: Jason Syrotuck <jasyrotuck@gmail.com>
License-File: LICENSE
Keywords: transparency,un,untp
Requires-Python: >=3.8
Requires-Dist: pydantic==2.7.1
